{
  "totalComplaints": 46,
  "numberOfFilteredComplaintMapKeys": 3,
  "filteredComplaintMapKeys": [
    "STEERING",
    "SEAT BELTS",
    "ELECTRICAL SYSTEM"
  ],
  "parsedComplaintsResultLength": 5,
  "parsedComplaintsResult": [
    {
      "complaintNumber": 1,
      "issueCategory": "Electric Power Steering Failure",
      "impact": "The failure of the electric power steering system can cause the loss of power assist, making it difficult or impossible to steer the vehicle, which can lead to accidents or loss of control.",
      "symptoms": [
        "The power steering warning message displays on the dashboard",
        "the power steering assist is lost",
        "the steering wheel becomes hard to turn",
        "the vehicle is difficult to control",
        "and the steering system may reset after turning off and restarting the vehicle."
      ],
      "odiNumbers": [
        "11540478",
        "11477699",
        "11459571",
        "11325153",
        "11219265",
        "11195409",
        "11144217",
        "11075266",
        "11011949",
        "11010446",
        "11005569",
        "11002448",
        "10993459",
        "10992987",
        "10979401",
        "10972321",
        "10971902",
        "10970645",
        "10956052",
        "10954442",
        "10948931",
        "10925243",
        "10914443",
        "10910138",
        "10905599",
        "10904409",
        "10903278"
      ],
      "relatedIssues": [],
      "relatedMaintenance": []
    },
    {
      "complaintNumber": 2,
      "issueCategory": "Steering Gear Assembly Failure",
      "impact": "The failure of the steering gear assembly can cause the loss of power assist, making it difficult or impossible to steer the vehicle, which can lead to accidents or loss of control.",
      "symptoms": [
        "The power steering warning message displays on the dashboard",
        "the power steering assist is lost",
        "the steering wheel becomes hard to turn",
        "the vehicle is difficult to control",
        "and the steering system may reset after turning off and restarting the vehicle."
      ],
      "odiNumbers": [
        "11325153",
        "10993459",
        "10948931"
      ],
      "relatedIssues": [],
      "relatedMaintenance": []
    },
    {
      "complaintNumber": 3,
      "issueCategory": "Recall Repair Issues",
      "impact": "The failure to properly repair the electric power steering system under recall can cause the loss of power assist, making it difficult or impossible to steer the vehicle, which can lead to accidents or loss of control.",
      "symptoms": [
        "The power steering warning message displays on the dashboard",
        "the power steering assist is lost",
        "the steering wheel becomes hard to turn",
        "the vehicle is difficult to control",
        "and the steering system may reset after turning off and restarting the vehicle."
      ],
      "odiNumbers": [
        "11436616",
        "11219265",
        "11011949",
        "10992987",
        "10904409"
      ],
      "relatedIssues": [],
      "relatedMaintenance": []
    },
    {
      "complaintNumber": 1,
      "issueCategory": "Seatbelt Cable Failure",
      "impact": "The failure of the seatbelt cable can cause the seatbelt to detach or break, leaving the driver and passengers without proper restraint, which can lead to serious injury or death in the event of an accident.",
      "symptoms": [
        "The seatbelt cable breaks or detaches",
        "the seatbelt cannot be secured",
        "the seatbelt pulls out of its anchor point",
        "the seatbelt shows signs of wear or damage."
      ],
      "odiNumbers": [
        "11429323",
        "11428446",
        "11340893",
        "10924709"
      ],
      "relatedIssues": [],
      "relatedMaintenance": []
    },
    {
      "complaintNumber": 4,
      "issueCategory": "Excessive Idle Power Drain by OnStar Module",
      "impact": "The excessive idle power drain by the OnStar module can cause the car battery to drain rapidly, leading to battery death, even when the vehicle is not in use, leaving the driver stranded and potentially causing safety issues.",
      "symptoms": [
        "The car battery dies or is drained rapidly",
        "even when the vehicle is not in use",
        "the vehicle is unable to start",
        "the battery is consistently drained when the vehicle is not driven for an extended period."
      ],
      "odiNumbers": [
        "11533019"
      ],
      "relatedIssues": [],
      "relatedMaintenance": []
    }
  ]
}