{
  "totalComplaints": 48,
  "numberOfFilteredComplaintMapKeys": 3,
  "filteredComplaintMapKeys": [
    "ENGINE AND ENGINE COOLING",
    "FUEL SYSTEM",
    "ELECTRICAL SYSTEM"
  ],
  "parsedComplaintsResultLength": 14,
  "parsedComplaintsResult": [
    {
      "complaintNumber": 1,
      "issueCategory": "Engine Failure and Explosions",
      "impact": "Engine failure and explosions can cause loss of vehicle control, accidents, and potentially life-threatening situations.",
      "symptoms": [
        "Engine stalling",
        "loud explosions",
        "smoke",
        "backfires",
        "and engine overheating."
      ],
      "odiNumbers": [
        "898587",
        "739160",
        "865663",
        "713570",
        "781468",
        "828162",
        "818696",
        "812524"
      ],
      "relatedIssues": [],
      "relatedMaintenance": []
    },
    {
      "complaintNumber": 2,
      "issueCategory": "Fuel System Failure",
      "impact": "Fuel system failure can cause engine stalling, loss of power, and potentially lead to accidents.",
      "symptoms": [
        "Fuel pressure regulator explosion",
        "engine stalling",
        "and loss of power."
      ],
      "odiNumbers": [
        "898587",
        "485563"
      ],
      "relatedIssues": [],
      "relatedMaintenance": []
    },
    {
      "complaintNumber": 3,
      "issueCategory": "Engine Cooling System Failure",
      "impact": "Engine cooling system failure can cause engine overheating, leading to engine damage and potentially causing accidents.",
      "symptoms": [
        "Engine overheating",
        "blown head gasket",
        "and oil cooler hose strap installation."
      ],
      "odiNumbers": [
        "739160",
        "485563"
      ],
      "relatedIssues": [],
      "relatedMaintenance": []
    },
    {
      "complaintNumber": 4,
      "issueCategory": "Engine Oil Leaks",
      "impact": "Engine oil leaks can cause engine damage, loss of power, and potentially lead to accidents.",
      "symptoms": [
        "Oil dripping from the pan into the exhaust system",
        "oil cooler hose strap installation."
      ],
      "odiNumbers": [
        "10117122",
        "485563"
      ],
      "relatedIssues": [],
      "relatedMaintenance": []
    },
    {
      "complaintNumber": 5,
      "issueCategory": "Ignition and Starting System Failure",
      "impact": "Ignition and starting system failure can cause engine stalling, loss of power, and potentially lead to accidents.",
      "symptoms": [
        "Engine stalling upon braking",
        "loud exploding noise when starting the engine."
      ],
      "odiNumbers": [
        "485563",
        "818696",
        "812524"
      ],
      "relatedIssues": [],
      "relatedMaintenance": []
    },
    {
      "complaintNumber": 1,
      "issueCategory": "Intake Manifold Failure",
      "impact": "The failure of the intake manifold can cause the engine to backfire, resulting in loud explosions, white smoke, and potential fires, which can lead to accidents or damage to the vehicle.",
      "symptoms": [
        "Loud backfire or explosion on starting",
        "engine running at full throttle",
        "intake manifold blown out",
        "smoke coming from the engine",
        "vehicle unoperative."
      ],
      "odiNumbers": [
        "10018260",
        "743686",
        "821671",
        "520354"
      ],
      "relatedIssues": [],
      "relatedMaintenance": []
    },
    {
      "complaintNumber": 2,
      "issueCategory": "Fuel Pump Failure",
      "impact": "The failure of the fuel pump can cause the engine to quit working, resulting in loss of power and potential accidents.",
      "symptoms": [
        "Engine quitting while driving",
        "fuel pump replacement required."
      ],
      "odiNumbers": [
        "882805",
        "485563"
      ],
      "relatedIssues": [],
      "relatedMaintenance": []
    },
    {
      "complaintNumber": 3,
      "issueCategory": "Fuel System Leaks",
      "impact": "Leaks in the fuel system can cause fires in the engine compartment, resulting in damage to the vehicle and potential accidents.",
      "symptoms": [
        "Fuel tank leaking",
        "fuel feed and return lines not fully assembled and locked",
        "fuel leaks."
      ],
      "odiNumbers": [
        "821378",
        "485563"
      ],
      "relatedIssues": [],
      "relatedMaintenance": []
    },
    {
      "complaintNumber": 4,
      "issueCategory": "Fuel Gauge Failure",
      "impact": "The failure of the fuel gauge can cause the driver to be unaware of the fuel level, leading to potential accidents or strandings.",
      "symptoms": [
        "Gas gauge fails to show the amount of fuel."
      ],
      "odiNumbers": [
        "984112"
      ],
      "relatedIssues": [],
      "relatedMaintenance": []
    },
    {
      "complaintNumber": 5,
      "issueCategory": "Fuel Injection System Malfunction",
      "impact": "Malfunction of the fuel injection system can cause fires in the engine, resulting in damage to the vehicle and potential accidents.",
      "symptoms": [
        "Fuel injection system malfunctioning",
        "fire in the engine."
      ],
      "odiNumbers": [
        "550778"
      ],
      "relatedIssues": [],
      "relatedMaintenance": []
    },
    {
      "complaintNumber": 4,
      "issueCategory": "Electrical System Failure",
      "impact": "The failure of the electrical system can cause the instrument panel lights to dim, the air conditioner compressor to shut off, and warning lights to illuminate, which can lead to distractions while driving, decreased visibility, and potential accidents.",
      "symptoms": [
        "Instrument panel lights dim",
        "air conditioner compressor shuts off",
        "warning lights illuminate (e.g. service ride control)",
        "fuel odor inside the vehicle",
        "engine stalling",
        "rough idling."
      ],
      "odiNumbers": [
        "10821062",
        "485563"
      ],
      "relatedIssues": [],
      "relatedMaintenance": []
    },
    {
      "complaintNumber": 5,
      "issueCategory": "Ignition System Failure",
      "impact": "The failure of the ignition system can cause the engine to stall, leading to a loss of power and control, which can increase the risk of accidents.",
      "symptoms": [
        "Engine stalling",
        "rough idling."
      ],
      "odiNumbers": [
        "485563"
      ],
      "relatedIssues": [],
      "relatedMaintenance": []
    },
    {
      "complaintNumber": 6,
      "issueCategory": "Battery Failure",
      "impact": "The failure of the battery can cause the engine to stall, leading to a loss of power and control, which can increase the risk of accidents.",
      "symptoms": [
        "Engine stalling."
      ],
      "odiNumbers": [
        "485563"
      ],
      "relatedIssues": [],
      "relatedMaintenance": []
    },
    {
      "complaintNumber": 7,
      "issueCategory": "Spark Plug Failure",
      "impact": "The failure of the spark plugs can cause the engine to idle roughly, leading to decreased engine performance and potential engine damage.",
      "symptoms": [
        "Rough idling."
      ],
      "odiNumbers": [
        "485563"
      ],
      "relatedIssues": [],
      "relatedMaintenance": []
    }
  ]
}