{
  "totalComplaints": 1334,
  "numberOfFilteredComplaintMapKeys": 4,
  "filteredComplaintMapKeys": [
    "ENGINE AND ENGINE COOLING",
    "POWER TRAIN",
    "FUEL SYSTEM",
    "AIR BAGS"
  ],
  "parsedComplaintsResultLength": 11,
  "parsedComplaintsResult": [
    {
      "complaintNumber": 1,
      "issueCategory": "Serpentine Belt Failure",
      "impact": "The failure of the serpentine belt can cause the loss of power steering, leading to accidents or loss of control, especially at high speeds.",
      "symptoms": [
        "The serpentine belt comes off the engine",
        "especially in rainy or snowy conditions",
        "causing loss of power steering",
        "overheating",
        "and potential engine damage."
      ],
      "odiNumbers": [
        "10616919",
        "10240784",
        "10224278",
        "10220956",
        "10119687",
        "10058023",
        "10057596",
        "10010869"
      ],
      "relatedIssues": [],
      "relatedMaintenance": []
    },
    {
      "complaintNumber": 2,
      "issueCategory": "Transmission Failure",
      "impact": "Transmission failure can cause the vehicle to stall or lose power, leading to accidents or loss of control.",
      "symptoms": [
        "The transmission slips out of gear",
        "causing the vehicle to stall or lose power",
        "especially when accelerating or decelerating."
      ],
      "odiNumbers": [
        "10110774",
        "10010188",
        "10008764",
        "10006175"
      ],
      "relatedIssues": [],
      "relatedMaintenance": []
    },
    {
      "complaintNumber": 3,
      "issueCategory": "Electrical System Failure",
      "impact": "Electrical system failure can cause the vehicle to stall or lose power, leading to accidents or loss of control.",
      "symptoms": [
        "The windshield wiper motor fails",
        "the check engine light illuminates",
        "and the vehicle stalls or loses power",
        "especially when driving at high speeds."
      ],
      "odiNumbers": [
        "10014882",
        "10010188",
        "10008764",
        "8019647"
      ],
      "relatedIssues": [],
      "relatedMaintenance": []
    },
    {
      "complaintNumber": 4,
      "issueCategory": "Engine Failure",
      "impact": "Engine failure can cause the vehicle to stall or lose power, leading to accidents or loss of control.",
      "symptoms": [
        "The engine fails",
        "causing the vehicle to stall or lose power",
        "especially when driving at high speeds."
      ],
      "odiNumbers": [
        "10029061",
        "10029981",
        "10024200",
        "10017248",
        "8019014"
      ],
      "relatedIssues": [],
      "relatedMaintenance": []
    },
    {
      "complaintNumber": 5,
      "issueCategory": "Fuel System Failure",
      "impact": "Fuel system failure can cause the vehicle to stall or lose power, leading to accidents or loss of control.",
      "symptoms": [
        "The fuel pump fails",
        "causing the vehicle to stall or lose power",
        "especially when driving at high speeds."
      ],
      "odiNumbers": [
        "10057839",
        "10006175",
        "8019014"
      ],
      "relatedIssues": [],
      "relatedMaintenance": []
    },
    {
      "complaintNumber": 1,
      "issueCategory": "Automatic Transmission Failure",
      "impact": "The failure of the automatic transmission can cause the vehicle to lose power, stall, or become stuck in gear, which can lead to accidents, injuries, or leave the driver stranded.",
      "symptoms": [
        "The transmission fails to shift gears",
        "the vehicle hesitates or jerks when shifting",
        "the transmission slips or hesitates when accelerating",
        "the vehicle stalls or loses power",
        "loud clunking or grinding noises from the transmission",
        "transmission fluid leaks."
      ],
      "odiNumbers": [
        "10177453",
        "10164647",
        "10133409",
        "10105822",
        "10104540",
        "10094157",
        "10093085",
        "10087807",
        "10086666",
        "10086214",
        "10084039",
        "10076153",
        "10073663",
        "10065613",
        "10059528",
        "10063006",
        "10060799",
        "10056227",
        "10052571",
        "10052174",
        "10022191",
        "10041802",
        "10032012",
        "10030097",
        "10027213",
        "10022622",
        "10020702",
        "10017736",
        "10017156"
      ],
      "relatedIssues": [],
      "relatedMaintenance": []
    },
    {
      "complaintNumber": 1,
      "issueCategory": "Fuel Tank Leaks and Rusted Fuel Filler Neck",
      "impact": "Fuel leaks from the fuel tank and rusted fuel filler neck can cause fires, explosions, and accidents, potentially leading to serious injuries or fatalities.",
      "symptoms": [
        "Fuel smell inside the vehicle",
        "fuel leaking from the fuel tank",
        "fuel pouring out from under the car",
        "gas spills when refueling",
        "fuel leaks when the tank is full",
        "fuel leaks from the top of the fuel tank",
        "fuel tank cracking and leaking fuel."
      ],
      "odiNumbers": [
        "10562047",
        "10228430",
        "10223788",
        "10177640",
        "10142685",
        "10140615",
        "10137687",
        "10130138",
        "10135283",
        "10108206",
        "10128077",
        "10059399",
        "10044106",
        "10029603",
        "10008899",
        "10006883",
        "10004123",
        "10002532",
        "10000064",
        "8023006",
        "769555",
        "8021313",
        "8020219",
        "567480",
        "8017389",
        "766087",
        "8015804",
        "8013216",
        "8012964"
      ],
      "relatedIssues": [],
      "relatedMaintenance": []
    },
    {
      "complaintNumber": 2,
      "issueCategory": "Fuel Rail Leaks and Cross-Over Tube O-Ring Failure",
      "impact": "Fuel rail leaks and cross-over tube O-ring failure can cause fires, explosions, and accidents, potentially leading to serious injuries or fatalities.",
      "symptoms": [
        "Fuel smell inside the vehicle",
        "fuel leaking from the fuel rail",
        "fuel rail leaking that could have started a fire under the hood",
        "fuel rail cross-over tube O-ring failure",
        "fuel leaks from the fuel rail."
      ],
      "odiNumbers": [
        "10108206",
        "10128077",
        "10059399",
        "10004123",
        "10000064",
        "8023006",
        "8013216"
      ],
      "relatedIssues": [],
      "relatedMaintenance": []
    },
    {
      "complaintNumber": 1,
      "issueCategory": "Airbag Clock Spring Failure",
      "impact": "The failure of the airbag clock spring can cause the airbag light to illuminate, rendering the airbag system inoperable, which can lead to serious injury or death in the event of a crash.",
      "symptoms": [
        "The airbag light stays on",
        "the horn is inoperative",
        "the cruise control is inoperative",
        "and the airbag system fails to deploy in the event of a crash."
      ],
      "odiNumbers": [
        "10079706",
        "10078708",
        "10065374",
        "10058700",
        "10052359",
        "10046281",
        "10041806",
        "10042158",
        "10028349",
        "10021521",
        "10015966",
        "10009778",
        "10009828",
        "10004360",
        "10004202",
        "10006817",
        "10006665",
        "770848",
        "770099",
        "10008551",
        "8021691",
        "768645",
        "567884",
        "8019910",
        "8019664",
        "767766",
        "8019120",
        "767207"
      ],
      "relatedIssues": [],
      "relatedMaintenance": []
    },
    {
      "complaintNumber": 2,
      "issueCategory": "Airbag Failure to Deploy",
      "impact": "The failure of the airbag system to deploy in the event of a crash can lead to serious injury or death.",
      "symptoms": [
        "The airbag fails to deploy in the event of a crash",
        "resulting in injury or death."
      ],
      "odiNumbers": [
        "10221428",
        "10079706",
        "10078708",
        "10024767",
        "10009828",
        "8019664"
      ],
      "relatedIssues": [],
      "relatedMaintenance": []
    },
    {
      "complaintNumber": 3,
      "issueCategory": "Cruise Control and Horn Failure",
      "impact": "The failure of the cruise control and horn can cause distraction and increase the risk of accidents.",
      "symptoms": [
        "The cruise control is inoperative",
        "and the horn is inoperative or sounds intermittently."
      ],
      "odiNumbers": [
        "10058700",
        "10052359",
        "10046281",
        "10041806",
        "10009778",
        "10006817",
        "10006665",
        "8021691",
        "768645",
        "8019120"
      ],
      "relatedIssues": [],
      "relatedMaintenance": []
    }
  ]
}