{
  "totalComplaints": 288,
  "numberOfFilteredComplaintMapKeys": 3,
  "filteredComplaintMapKeys": [
    "POWER TRAIN",
    "UNKNOWN OR OTHER",
    "STEERING"
  ],
  "parsedComplaintsResultLength": 13,
  "parsedComplaintsResult": [
    {
      "complaintNumber": 1,
      "issueCategory": "Torque Converter Failure",
      "impact": "The failure of the torque converter can cause the vehicle to shudder, jerk, or hesitate while accelerating, which can lead to accidents or leave the driver stranded.",
      "symptoms": [
        "The vehicle shudders or jerks while accelerating",
        "hesitation while accelerating",
        "loss of power",
        "transmission shuttering",
        "vehicle stalls",
        "and sudden slowing down or stopping."
      ],
      "odiNumbers": [
        "11574605",
        "11463577",
        "11447708",
        "11445190",
        "11442629",
        "11437141",
        "11433297",
        "11429320",
        "11408161",
        "11397629",
        "11365593",
        "11362453",
        "11338813",
        "11291938",
        "11288871",
        "11267117",
        "11245370",
        "11189682",
        "11179854",
        "11176157",
        "11176410",
        "11160708",
        "11153181",
        "11111795",
        "11111077",
        "11098296",
        "11074330"
      ],
      "relatedIssues": [],
      "relatedMaintenance": []
    },
    {
      "complaintNumber": 2,
      "issueCategory": "Transmission Malfunction",
      "impact": "The transmission malfunction can cause the vehicle to hesitate, shudder, or jerk while accelerating, which can lead to accidents or leave the driver stranded.",
      "symptoms": [
        "The vehicle hesitates or shudders while accelerating",
        "transmission shuttering",
        "loss of power",
        "vehicle stalls",
        "and sudden slowing down or stopping."
      ],
      "odiNumbers": [
        "11463577",
        "11447708",
        "11445190",
        "11442629",
        "11437141",
        "11433297",
        "11429320",
        "11408161",
        "11397629",
        "11365593",
        "11362453",
        "11338813",
        "11291938",
        "11288871",
        "11267117",
        "11245370",
        "11189682",
        "11179854",
        "11176157",
        "11176410",
        "11160708",
        "11153181",
        "11111795",
        "11111077",
        "11098296",
        "11074330"
      ],
      "relatedIssues": [],
      "relatedMaintenance": []
    },
    {
      "complaintNumber": 3,
      "issueCategory": "Clutch Malfunction",
      "impact": "The clutch malfunction can cause the vehicle to hesitate, shudder, or jerk while accelerating, which can lead to accidents or leave the driver stranded.",
      "symptoms": [
        "The vehicle hesitates or shudders while accelerating",
        "clutch pedal feels soft or spongy",
        "clutch pedal sticks to the floor",
        "and sudden slowing down or stopping."
      ],
      "odiNumbers": [
        "11587985",
        "11362453"
      ],
      "relatedIssues": [],
      "relatedMaintenance": []
    },
    {
      "complaintNumber": 1,
      "issueCategory": "Torque Converter Failure",
      "impact": "The failure of the torque converter can cause the vehicle to shudder or hesitate when accelerating, which can lead to loss of control and accidents.",
      "symptoms": [
        "The vehicle shudders or hesitates when accelerating",
        "especially between 25-50 mph."
      ],
      "odiNumbers": [
        "11467238",
        "11436338",
        "10959094"
      ],
      "relatedIssues": [],
      "relatedMaintenance": []
    },
    {
      "complaintNumber": 2,
      "issueCategory": "Transmission Issues",
      "impact": "Transmission issues can cause the vehicle to hesitate or shudder when accelerating, leading to loss of control and accidents.",
      "symptoms": [
        "The vehicle hesitates or shudders when accelerating",
        "especially when shifting into gear."
      ],
      "odiNumbers": [
        "11234993",
        "11093659"
      ],
      "relatedIssues": [],
      "relatedMaintenance": []
    },
    {
      "complaintNumber": 3,
      "issueCategory": "Sunroof Explosions",
      "impact": "The sudden explosion of the sunroof can cause damage to the vehicle and potentially injure occupants.",
      "symptoms": [
        "The sunroof shatters or explodes without warning",
        "often with a loud noise."
      ],
      "odiNumbers": [
        "11394750",
        "11300478",
        "11205145",
        "11205146",
        "11205151",
        "11205152",
        "11205177"
      ],
      "relatedIssues": [],
      "relatedMaintenance": []
    },
    {
      "complaintNumber": 4,
      "issueCategory": "Air Conditioning Issues",
      "impact": "Musty or musky odors from the air conditioning system can cause discomfort and health issues for occupants.",
      "symptoms": [
        "The air conditioning system emits a musty or musky odor."
      ],
      "odiNumbers": [
        "11181637",
        "10994268"
      ],
      "relatedIssues": [],
      "relatedMaintenance": []
    },
    {
      "complaintNumber": 5,
      "issueCategory": "Audio System Issues",
      "impact": "Malfunctioning audio systems can cause distractions while driving, leading to accidents.",
      "symptoms": [
        "The audio system fails to function properly",
        "with issues such as loading errors",
        "poor tuning",
        "and insensitive touch screens."
      ],
      "odiNumbers": [
        "11175107",
        "11161013"
      ],
      "relatedIssues": [],
      "relatedMaintenance": []
    },
    {
      "complaintNumber": 6,
      "issueCategory": "Fuel System Issues",
      "impact": "Fuel system issues can cause the vehicle to stall or fail to start, leading to accidents or strandings.",
      "symptoms": [
        "The vehicle emits a strong",
        "unpleasant odor",
        "especially when accelerating."
      ],
      "odiNumbers": [
        "11131767",
        "11058146"
      ],
      "relatedIssues": [],
      "relatedMaintenance": []
    },
    {
      "complaintNumber": 7,
      "issueCategory": "Door Lock Issues",
      "impact": "Malfunctioning door locks can cause inconvenience and safety risks, especially if the doors fail to lock or unlock properly.",
      "symptoms": [
        "The door locks fail to function properly",
        "with issues such as remote lock/unlock failure and powered door lock failure."
      ],
      "odiNumbers": [
        "11115604",
        "11115607"
      ],
      "relatedIssues": [],
      "relatedMaintenance": []
    },
    {
      "complaintNumber": 1,
      "issueCategory": "Electrical Steering Failure",
      "impact": "The failure of the electrical steering system can cause the power steering to malfunction, leading to a loss of control, accidents, and injuries.",
      "symptoms": [
        "The steering wheel becomes hard to turn",
        "the power steering light comes on",
        "the steering wheel shakes violently",
        "the vehicle wanders or drifts to one side",
        "the airbag light comes on",
        "and the radio and other electrical systems malfunction."
      ],
      "odiNumbers": [
        "11323055",
        "11271387",
        "11218440",
        "11097894",
        "11093665",
        "10918544",
        "10874838",
        "10850471",
        "10735577",
        "10733493",
        "10681901",
        "10644043",
        "10629753",
        "10628029",
        "10618899",
        "10605871",
        "10585036",
        "10573998",
        "10573136",
        "10564129",
        "10557954",
        "10551428",
        "10549963",
        "10544465",
        "10532564",
        "10522403",
        "10513767"
      ],
      "relatedIssues": [],
      "relatedMaintenance": []
    },
    {
      "complaintNumber": 2,
      "issueCategory": "Airbag System Failure",
      "impact": "The failure of the airbag system can lead to a failure to deploy in the event of an accident, resulting in serious injuries or fatalities.",
      "symptoms": [
        "The airbag light comes on",
        "the airbag system malfunctions",
        "and the airbags fail to deploy in the event of an accident."
      ],
      "odiNumbers": [
        "11323055",
        "11097894",
        "10573136",
        "10557954"
      ],
      "relatedIssues": [],
      "relatedMaintenance": []
    },
    {
      "complaintNumber": 3,
      "issueCategory": "Vehicle Stalling and Acceleration Issues",
      "impact": "The vehicle stalling and acceleration issues can lead to a loss of control, accidents, and injuries.",
      "symptoms": [
        "The vehicle stalls or accelerates unexpectedly",
        "the vehicle wanders or drifts to one side",
        "and the power steering light comes on."
      ],
      "odiNumbers": [
        "11100664",
        "10874838",
        "10551428"
      ],
      "relatedIssues": [],
      "relatedMaintenance": []
    }
  ]
}