{
  "totalComplaints": 125,
  "numberOfFilteredComplaintMapKeys": 3,
  "filteredComplaintMapKeys": [
    "POWER TRAIN",
    "ENGINE",
    "UNKNOWN OR OTHER"
  ],
  "parsedComplaintsResultLength": 19,
  "parsedComplaintsResult": [
    {
      "complaintNumber": 1,
      "issueCategory": "Loss of Power and Acceleration",
      "impact": "The loss of power and acceleration can cause the vehicle to slow down or stall, increasing the risk of accidents, especially when driving on highways or merging with traffic.",
      "symptoms": [
        "The vehicle loses power",
        "accelerates slowly",
        "or stalls; the check engine light may illuminate; the vehicle may jerk or vibrate; and the transmission may shift into a lower gear."
      ],
      "odiNumbers": [
        "11591693",
        "11580960",
        "11572626",
        "11566535",
        "11537412",
        "11528418",
        "11520987",
        "11519179",
        "11515777",
        "11511809",
        "11505252",
        "11498602",
        "11497633"
      ],
      "relatedIssues": [],
      "relatedMaintenance": []
    },
    {
      "complaintNumber": 2,
      "issueCategory": "Transmission Failure and Error Messages",
      "impact": "Transmission failure can cause the vehicle to lose power, stall, or become stuck in gear, increasing the risk of accidents and stranding the driver.",
      "symptoms": [
        "The transmission system error message is displayed; the vehicle jerks or vibrates; the transmission shifts into a lower gear; and the vehicle loses power or accelerates slowly."
      ],
      "odiNumbers": [
        "11501628",
        "11498602",
        "11497633",
        "11511809",
        "11505252",
        "11502340",
        "11502371",
        "11498519",
        "11497998",
        "11497702",
        "11497187"
      ],
      "relatedIssues": [],
      "relatedMaintenance": []
    },
    {
      "complaintNumber": 3,
      "issueCategory": "Clutch and Hydraulic System Failure",
      "impact": "Clutch and hydraulic system failure can cause the vehicle to lose power, stall, or become stuck in gear, increasing the risk of accidents and stranding the driver.",
      "symptoms": [
        "The clutch pedal feels soft or spongy; the clutch pedal sticks to the floor; the clutch pedal does not return to its normal position; and the vehicle loses power or accelerates slowly."
      ],
      "odiNumbers": [
        "11579130",
        "11578546",
        "11578047"
      ],
      "relatedIssues": [],
      "relatedMaintenance": []
    },
    {
      "complaintNumber": 4,
      "issueCategory": "Hybrid System Failure and Error Messages",
      "impact": "Hybrid system failure can cause the vehicle to lose power, stall, or become stuck in gear, increasing the risk of accidents and stranding the driver.",
      "symptoms": [
        "The check hybrid system stop safely alert is displayed; the vehicle loses power or accelerates slowly; the battery gauge drains rapidly; and the vehicle may not start."
      ],
      "odiNumbers": [
        "11528418",
        "11520987"
      ],
      "relatedIssues": [],
      "relatedMaintenance": []
    },
    {
      "complaintNumber": 5,
      "issueCategory": "Recall Repair Delays and Parts Unavailability",
      "impact": "Delays in recall repairs and parts unavailability can leave vehicles on the road with known safety issues, increasing the risk of accidents and injuries.",
      "symptoms": [
        "The vehicle is under recall",
        "but the parts are not available; the dealer is unable to perform the recall repair; and the manufacturer has exceeded a reasonable amount of time for the recall repair."
      ],
      "odiNumbers": [
        "11511809",
        "11505252",
        "11502340",
        "11502371",
        "11498519",
        "11497998",
        "11497702",
        "11497187"
      ],
      "relatedIssues": [],
      "relatedMaintenance": []
    },
    {
      "complaintNumber": 1,
      "issueCategory": "Fuel Injector Failure",
      "impact": "The failure of fuel injectors can cause the engine to misfire, leading to a loss of power, stalling, and potentially causing accidents or stranding the driver.",
      "symptoms": [
        "Engine misfire",
        "loss of power",
        "stalling",
        "rough idle",
        "hesitation",
        "and difficulty accelerating."
      ],
      "odiNumbers": [
        "11569061",
        "11557573",
        "11549488",
        "11543928",
        "11513300"
      ],
      "relatedIssues": [],
      "relatedMaintenance": []
    },
    {
      "complaintNumber": 2,
      "issueCategory": "Clutch and Transmission Issues",
      "impact": "The failure of the clutch and transmission can cause the vehicle to lose power, stall, or fail to shift gears, leading to accidents or stranding the driver.",
      "symptoms": [
        "Difficulty shifting gears",
        "loss of power",
        "stalling",
        "hesitation",
        "and unusual noises or vibrations."
      ],
      "odiNumbers": [
        "11569061",
        "11478308"
      ],
      "relatedIssues": [],
      "relatedMaintenance": []
    },
    {
      "complaintNumber": 3,
      "issueCategory": "Engine Oil Leaks and Contamination",
      "impact": "Engine oil leaks and contamination can cause engine damage, leading to a loss of power, stalling, and potentially causing accidents or stranding the driver.",
      "symptoms": [
        "Oil leaks",
        "oil contamination",
        "engine noise",
        "and loss of power."
      ],
      "odiNumbers": [
        "11498269"
      ],
      "relatedIssues": [],
      "relatedMaintenance": []
    },
    {
      "complaintNumber": 4,
      "issueCategory": "Inverter Cooling System Failure (Hybrid Vehicles)",
      "impact": "The failure of the inverter cooling system can cause the hybrid system to malfunction, leading to a loss of power, stalling, and potentially causing accidents or stranding the driver.",
      "symptoms": [
        "Warning lights",
        "loss of power",
        "stalling",
        "and unusual noises or vibrations."
      ],
      "odiNumbers": [
        "11510435",
        "11449369"
      ],
      "relatedIssues": [],
      "relatedMaintenance": []
    },
    {
      "complaintNumber": 5,
      "issueCategory": "Electronic Throttle Control Issues",
      "impact": "The failure of the electronic throttle control can cause the engine to stall or lose power, leading to accidents or stranding the driver.",
      "symptoms": [
        "Loss of power",
        "stalling",
        "hesitation",
        "and unusual noises or vibrations."
      ],
      "odiNumbers": [
        "11514215",
        "11493000",
        "11468923"
      ],
      "relatedIssues": [],
      "relatedMaintenance": []
    },
    {
      "complaintNumber": 6,
      "issueCategory": "Ignition System Issues",
      "impact": "The failure of the ignition system can cause the engine to stall or lose power, leading to accidents or stranding the driver.",
      "symptoms": [
        "Engine misfire",
        "loss of power",
        "stalling",
        "and unusual noises or vibrations."
      ],
      "odiNumbers": [
        "11513300"
      ],
      "relatedIssues": [],
      "relatedMaintenance": []
    },
    {
      "complaintNumber": 1,
      "issueCategory": "Sudden Loss of Power and Unstable Engine Performance",
      "impact": "The sudden loss of power and unstable engine performance can cause the vehicle to slow down or stall, increasing the risk of accidents, especially on highways.",
      "symptoms": [
        "The vehicle loses power",
        "RPM racing back and forth",
        "unable to exceed a certain speed",
        "sudden slowing down",
        "engine light turns on",
        "and a burning smell."
      ],
      "odiNumbers": [
        "11533214",
        "11516315"
      ],
      "relatedIssues": [],
      "relatedMaintenance": []
    },
    {
      "complaintNumber": 2,
      "issueCategory": "Sunroof/Moonroof Explosion",
      "impact": "The sudden explosion of the sunroof/moonroof can cause distraction, injury, or even accidents, especially if it occurs while driving.",
      "symptoms": [
        "The sunroof/moonroof explodes without warning",
        "causing a loud noise",
        "and potentially shattering glass."
      ],
      "odiNumbers": [
        "11552599",
        "11493395",
        "11479263"
      ],
      "relatedIssues": [],
      "relatedMaintenance": []
    },
    {
      "complaintNumber": 3,
      "issueCategory": "Windshield and Rubber Seal Issues",
      "impact": "The failure of the windshield and rubber seal can cause water to seep into the vehicle, leading to electrical issues, and potentially causing the windshield to crack or fall out, compromising the safety of the occupants.",
      "symptoms": [
        "The rubber seal around the windshield is pulling apart",
        "the windshield is chipping or cracking",
        "and water is seeping into the vehicle."
      ],
      "odiNumbers": [
        "11536124",
        "11533965"
      ],
      "relatedIssues": [],
      "relatedMaintenance": []
    },
    {
      "complaintNumber": 4,
      "issueCategory": "False Emergency Brake Activation",
      "impact": "The false activation of the emergency brake can cause the vehicle to slow down or stop suddenly, increasing the risk of accidents, especially on highways.",
      "symptoms": [
        "The vehicle suddenly beeps and displays an emergency brake warning",
        "slowing down the vehicle without any apparent reason."
      ],
      "odiNumbers": [
        "11528204"
      ],
      "relatedIssues": [],
      "relatedMaintenance": []
    },
    {
      "complaintNumber": 5,
      "issueCategory": "Fire Hazard due to Trailer Tow Hitch Recall",
      "impact": "The trailer tow hitch recall can cause the vehicle to catch fire while driving or parked, posing a significant risk to the occupants and others in the vicinity.",
      "symptoms": [
        "No warning lights or notifications",
        "but the vehicle is at risk of catching fire due to the trailer tow hitch recall."
      ],
      "odiNumbers": [
        "11525110"
      ],
      "relatedIssues": [],
      "relatedMaintenance": []
    },
    {
      "complaintNumber": 6,
      "issueCategory": "Gasoline Leak",
      "impact": "The gasoline leak can cause a hazardous waste spill, posing a significant risk to the occupants and others in the vicinity.",
      "symptoms": [
        "Gasoline is leaking from the vehicle at a rate of approximately one drop every two seconds."
      ],
      "odiNumbers": [
        "11441023"
      ],
      "relatedIssues": [],
      "relatedMaintenance": []
    },
    {
      "complaintNumber": 7,
      "issueCategory": "Transfer Case/Power Control Unit Failure",
      "impact": "The failure of the transfer case/power control unit can cause the vehicle to lose power and become unstable, increasing the risk of accidents.",
      "symptoms": [
        "The vehicle loses power",
        "and the transfer case/power control unit fails."
      ],
      "odiNumbers": [
        "11458499"
      ],
      "relatedIssues": [],
      "relatedMaintenance": []
    },
    {
      "complaintNumber": 8,
      "issueCategory": "Infotainment System Issues",
      "impact": "The infotainment system issues can cause distraction while driving, potentially leading to accidents.",
      "symptoms": [
        "The connection to WAZE via wireless car play is disconnected",
        "prompting the user to use a cable."
      ],
      "odiNumbers": [
        "11431311"
      ],
      "relatedIssues": [],
      "relatedMaintenance": []
    }
  ]
}